http_prober/__init__.py
http_prober/modules/__init__.py
http_prober/modules/core.py
http_prober/modules/cli/__init__.py
http_prober/modules/cli/cli.py
http_prober/modules/extender/__init__.py
http_prober/modules/extender/extender.py
http_prober/modules/prober/__init__.py
http_prober/modules/prober/prober.py
http_prober/modules/tests/__init__.py
http_prober/modules/tests/test_cli.py
http_prober/modules/tests/test_utils.py
http_prober/modules/utils/__init__.py
http_prober/modules/utils/utils.py
http_prober-1.1.2.dist-info/licenses/LICENSE
http_prober-1.1.2.dist-info/METADATA
http_prober-1.1.2.dist-info/WHEEL
http_prober-1.1.2.dist-info/entry_points.txt
http_prober-1.1.2.dist-info/top_level.txt
http_prober-1.1.2.dist-info/RECORD
