Metadata-Version: 2.4
Name: Http-Prober
Version: 1.1.2
Summary: An async http statuscode prober to enumerate status code from url(s).
Home-page: https://github.com/pevinkumar10/http-prober
Author: Pevinkumar A
Author-email: pevinbalaji@gmail.com
Classifier: Programming Language :: Python :: 3
Classifier: License :: OSI Approved :: MIT License
Requires-Python: >=3.6
License-File: LICENSE
Requires-Dist: aiohttp
Requires-Dist: colorama
Requires-Dist: resource
Requires-Dist: httpx
Dynamic: author
Dynamic: author-email
Dynamic: classifier
Dynamic: home-page
Dynamic: license-file
Dynamic: requires-dist
Dynamic: requires-python
Dynamic: summary
